composio_langchain/__init__.py
composio_langchain/provider.py
composio_langchain/py.typed
composio_langchain-0.10.7.dist-info/METADATA
composio_langchain-0.10.7.dist-info/WHEEL
composio_langchain-0.10.7.dist-info/top_level.txt
composio_langchain-0.10.7.dist-info/RECORD
